PingServer/__init__.py
PingServer/launch_pages_internal.py
PingServer-1.0.1.dist-info/LICENSE
PingServer-1.0.1.dist-info/METADATA
PingServer-1.0.1.dist-info/WHEEL
PingServer-1.0.1.dist-info/top_level.txt
PingServer-1.0.1.dist-info/RECORD
