Metadata-Version: 2.1
Name: PingServer
Version: 1.0.1
Summary: Makes creating a server to be pinged easier
Home-page: https://github.com/Necrownyx/PingServer
Author: Isaac
Author-email: necrownyx@outlook.com
License: UNKNOWN
Project-URL: Bug Tracker, https://github.com/Necrownyx/PingServer/issues
Platform: UNKNOWN
Classifier: Programming Language :: Python :: 3
Classifier: License :: OSI Approved :: MIT License
Classifier: Operating System :: OS Independent
Requires-Python: >=3.6
License-File: LICENSE
Requires-Dist: flask
